gradio_tokenizertextbox/__init__.py
gradio_tokenizertextbox/tokenizertextbox.py
gradio_tokenizertextbox/tokenizertextbox.pyi
gradio_tokenizertextbox/templates/component/Index-DcB-GfxT.js
gradio_tokenizertextbox/templates/component/_basePickBy-CmQMinPE.js
gradio_tokenizertextbox/templates/component/_baseUniq-CGPZBsyr.js
gradio_tokenizertextbox/templates/component/arc-Cu2DeyqI.js
gradio_tokenizertextbox/templates/component/architectureDiagram-KYWUMXXP-C8-HmmxG.js
gradio_tokenizertextbox/templates/component/blockDiagram-ZUX3OVTL-CPYM4uU3.js
gradio_tokenizertextbox/templates/component/c4Diagram-E5VUS4TQ-DEMLXh6u.js
gradio_tokenizertextbox/templates/component/channel-BOYrQ526.js
gradio_tokenizertextbox/templates/component/chunk-44GW5IO5-CgUpA7Lc.js
gradio_tokenizertextbox/templates/component/chunk-BQPDZTM5-H2f8qn0Z.js
gradio_tokenizertextbox/templates/component/chunk-GOYUR5SG-S260I3wK.js
gradio_tokenizertextbox/templates/component/chunk-HPOVUXKZ-CVYZ_LxH.js
gradio_tokenizertextbox/templates/component/chunk-UIWBPB2F-DzF7UJFk.js
gradio_tokenizertextbox/templates/component/chunk-WZLT4MVT-CCSRfGd_.js
gradio_tokenizertextbox/templates/component/chunk-YQZZRAKN-BkJpSkbb.js
gradio_tokenizertextbox/templates/component/classDiagram-EGQPL23Y-DMKykbn5.js
gradio_tokenizertextbox/templates/component/classDiagram-v2-4EBKGCBT-DMKykbn5.js
gradio_tokenizertextbox/templates/component/clone-B3_KUDh3.js
gradio_tokenizertextbox/templates/component/cytoscape.esm-C2cgT2B2.js
gradio_tokenizertextbox/templates/component/dagre-IE2X5DAH-BQaK-xNm.js
gradio_tokenizertextbox/templates/component/diagram-3XXCIKAB-Dw8mtPCi.js
gradio_tokenizertextbox/templates/component/diagram-DTTGSU4T-BNnNo3RB.js
gradio_tokenizertextbox/templates/component/erDiagram-FWMTN743-DdEXAbgz.js
gradio_tokenizertextbox/templates/component/flowDiagram-OUUYVNGO-Ba7G95Y6.js
gradio_tokenizertextbox/templates/component/ganttDiagram-Y4ZJHTSR-D19dQQDv.js
gradio_tokenizertextbox/templates/component/gitGraphDiagram-SOPYED2O-BX_PUCEk.js
gradio_tokenizertextbox-0.0.5.dist-info/METADATA
gradio_tokenizertextbox-0.0.5.dist-info/WHEEL
gradio_tokenizertextbox-0.0.5.dist-info/RECORD
